ocfl_s3_validator/__init__.py
ocfl_s3_validator/object_validator.py
ocfl_s3_validator/validation_result.py
ocfl_s3_validator-0.1.3.dist-info/METADATA
ocfl_s3_validator-0.1.3.dist-info/WHEEL
ocfl_s3_validator-0.1.3.dist-info/licenses/LICENSE
ocfl_s3_validator-0.1.3.dist-info/RECORD
