Metadata-Version: 2.4
Name: ocfl-s3-validator
Version: 0.1.3
Summary: A Python OCFL Object validator for content in S3
License-File: LICENSE
Requires-Python: >=3.12
Requires-Dist: ocfl-py>=1.3.0
Requires-Dist: python-dotenv>=1.0.1
